altinn3_test_lib/__init__.py
altinn3_test_lib/hello_test.py
altinn3_test_lib/plugins.py
altinn3_test_lib/fixtures/__init__.py
altinn3_test_lib/fixtures/factories/__init__.py
altinn3_test_lib/fixtures/factories/altinn_factory.py
altinn3_test_lib/fixtures/factories/file_factory.py
altinn3_test_lib/fixtures/factories/gcp_factories.py
altinn3_test_lib/fixtures/mocking/__init__.py
altinn3_test_lib/fixtures/mocking/environment_vars.py
altinn3_test_lib/fixtures/mocking/mock_assist.py
altinn3_test_lib/resources/__init__.py
altinn3_test_lib/resources/mocking.py
altinn3_test_lib/test_files/instance.json
altinn3_test_lib/test_files/instance_json_in.json
altinn3_test_lib/test_files/instance_json_out.json
altinn3_test_lib/test_files/simple_prefill.txt
altinn3_test_lib/utils/__init__.py
altinn3_test_lib/utils/fileutils.py
altinn3_test_lib-0.0.11.dist-info/METADATA
altinn3_test_lib-0.0.11.dist-info/WHEEL
altinn3_test_lib-0.0.11.dist-info/licenses/LICENSE
altinn3_test_lib-0.0.11.dist-info/RECORD
